plotbitrate.py
frame/__init__.py
frame/_frame_class.py
frame/_frame_dataclass.py
rezun_plotbitrate-1.0.6.dist-info/LICENSE
rezun_plotbitrate-1.0.6.dist-info/METADATA
rezun_plotbitrate-1.0.6.dist-info/WHEEL
rezun_plotbitrate-1.0.6.dist-info/entry_points.txt
rezun_plotbitrate-1.0.6.dist-info/top_level.txt
rezun_plotbitrate-1.0.6.dist-info/RECORD
