Metadata-Version: 2.1
Name: rezun-plotbitrate
Version: 1.0.6
Summary: A simple bitrate plotter for media files
Home-page: https://github.com/rezun/plotbitrate
Author: Steve Schmidt
Author-email: azcane@gmail.com
License: BSD
Keywords: ffprobe bitrate plot
Platform: UNKNOWN
Classifier: Topic :: Multimedia :: Sound/Audio
Classifier: Natural Language :: English
Classifier: Programming Language :: Python :: 3.5
Requires-Python: >=3.5
Requires-Dist: matplotlib
Requires-Dist: pyqt5
